{
  "videos": [
    {
      "publishedAt": "2022-03-14T09:21:29Z",
      "channelId": "UCNhy3hGzwMfbtX3Ei8Htcpg",
      "title": "Spring Meetup - Campus Eindhoven - 24/03/2022",
      "description": "Michael Jorissen (iO) – Impact of 3D in commerce Eddy Vinck (iO) - Getting Started with Remix and a Headless CMS.",
      "thumbnails": {
        "default": {
          "url": "https://i.ytimg.com/vi/YdEK3kDNQvg/default_live.jpg",
          "width": 120,
          "height": 90
        },
        "medium": {
          "url": "https://i.ytimg.com/vi/YdEK3kDNQvg/mqdefault_live.jpg",
          "width": 320,
          "height": 180
        },
        "high": {
          "url": "https://i.ytimg.com/vi/YdEK3kDNQvg/hqdefault_live.jpg",
          "width": 480,
          "height": 360
        }
      },
      "channelTitle": "iO - Technology",
      "liveBroadcastContent": "upcoming",
      "publishTime": "2022-03-14T09:21:29Z",
      "id": "YdEK3kDNQvg"
    },
    {
      "publishedAt": "2022-02-24T04:46:49Z",
      "channelId": "UCNhy3hGzwMfbtX3Ei8Htcpg",
      "title": "Front-end Meetup - Guru talks",
      "description": "This time it's a home game with two of our own Developer Advocates: Maarten van Hoof and Abbe Keultjes! On February, 23rd at ...",
      "thumbnails": {
        "default": {
          "url": "https://i.ytimg.com/vi/EFR11w2FicE/default.jpg",
          "width": 120,
          "height": 90
        },
        "medium": {
          "url": "https://i.ytimg.com/vi/EFR11w2FicE/mqdefault.jpg",
          "width": 320,
          "height": 180
        },
        "high": {
          "url": "https://i.ytimg.com/vi/EFR11w2FicE/hqdefault.jpg",
          "width": 480,
          "height": 360
        }
      },
      "channelTitle": "iO - Technology",
      "liveBroadcastContent": "none",
      "publishTime": "2022-02-24T04:46:49Z",
      "id": "EFR11w2FicE"
    },
    {
      "publishedAt": "2022-01-20T13:23:16Z",
      "channelId": "UCNhy3hGzwMfbtX3Ei8Htcpg",
      "title": "Building excellent user experiences with Remix - Kent C. Dodds | GURU TALKS",
      "description": "Remix is a Web Framework that uses the web platform to enable you to build excellent user experiences. In this talk Kent shows ...",
      "thumbnails": {
        "default": {
          "url": "https://i.ytimg.com/vi/r2Gks2qm0AY/default.jpg",
          "width": 120,
          "height": 90
        },
        "medium": {
          "url": "https://i.ytimg.com/vi/r2Gks2qm0AY/mqdefault.jpg",
          "width": 320,
          "height": 180
        },
        "high": {
          "url": "https://i.ytimg.com/vi/r2Gks2qm0AY/hqdefault.jpg",
          "width": 480,
          "height": 360
        }
      },
      "channelTitle": "iO - Technology",
      "liveBroadcastContent": "none",
      "publishTime": "2022-01-20T13:23:16Z",
      "id": "r2Gks2qm0AY"
    },
    {
      "publishedAt": "2021-12-13T07:27:30Z",
      "channelId": "UCNhy3hGzwMfbtX3Ei8Htcpg",
      "title": "Transforming JS &amp; TS codebases with Typescript compiler and ASTs - Albert Groothedde | GURU TALKS",
      "description": "Project from talk: https://github.com/alber70g/presentation-refactoring-ast Guide to create @angular-devkit/schematic: ...",
      "thumbnails": {
        "default": {
          "url": "https://i.ytimg.com/vi/DIxwVnoTQb8/default.jpg",
          "width": 120,
          "height": 90
        },
        "medium": {
          "url": "https://i.ytimg.com/vi/DIxwVnoTQb8/mqdefault.jpg",
          "width": 320,
          "height": 180
        },
        "high": {
          "url": "https://i.ytimg.com/vi/DIxwVnoTQb8/hqdefault.jpg",
          "width": 480,
          "height": 360
        }
      },
      "channelTitle": "iO - Technology",
      "liveBroadcastContent": "none",
      "publishTime": "2021-12-13T07:27:30Z",
      "id": "DIxwVnoTQb8"
    },
    {
      "publishedAt": "2021-12-13T07:27:15Z",
      "channelId": "UCNhy3hGzwMfbtX3Ei8Htcpg",
      "title": "Infrastructure as Code with AWS CDK - Juan Castellanos | GURU TALKS",
      "description": "AWS provides more than 100 services, and it can be quite difficult to get started. Creating Cloudformation templates in YAML or ...",
      "thumbnails": {
        "default": {
          "url": "https://i.ytimg.com/vi/VXfHQWzWAS4/default.jpg",
          "width": 120,
          "height": 90
        },
        "medium": {
          "url": "https://i.ytimg.com/vi/VXfHQWzWAS4/mqdefault.jpg",
          "width": 320,
          "height": 180
        },
        "high": {
          "url": "https://i.ytimg.com/vi/VXfHQWzWAS4/hqdefault.jpg",
          "width": 480,
          "height": 360
        }
      },
      "channelTitle": "iO - Technology",
      "liveBroadcastContent": "none",
      "publishTime": "2021-12-13T07:27:15Z",
      "id": "VXfHQWzWAS4"
    },
    {
      "publishedAt": "2021-11-18T07:33:43Z",
      "channelId": "UCNhy3hGzwMfbtX3Ei8Htcpg",
      "title": "Learnings using Web Components in an Enterprise - Justus Romijn | GURU TALKS",
      "description": "Justus will share his experiences of building and maintaining a big web component library at the Rabobank. He will offer tips, ...",
      "thumbnails": {
        "default": {
          "url": "https://i.ytimg.com/vi/rRdUhuD9QaQ/default.jpg",
          "width": 120,
          "height": 90
        },
        "medium": {
          "url": "https://i.ytimg.com/vi/rRdUhuD9QaQ/mqdefault.jpg",
          "width": 320,
          "height": 180
        },
        "high": {
          "url": "https://i.ytimg.com/vi/rRdUhuD9QaQ/hqdefault.jpg",
          "width": 480,
          "height": 360
        }
      },
      "channelTitle": "iO - Technology",
      "liveBroadcastContent": "none",
      "publishTime": "2021-11-18T07:33:43Z",
      "id": "rRdUhuD9QaQ"
    },
    {
      "publishedAt": "2021-11-18T07:33:29Z",
      "channelId": "UCNhy3hGzwMfbtX3Ei8Htcpg",
      "title": "One Web Component a day keeps the doctor away - Lucien Immink | GURU TALKS",
      "description": "Let's talk about web components and how they help to build scalable and maintainable applications. Do you need to replace your ...",
      "thumbnails": {
        "default": {
          "url": "https://i.ytimg.com/vi/KSZSd_jjTVg/default.jpg",
          "width": 120,
          "height": 90
        },
        "medium": {
          "url": "https://i.ytimg.com/vi/KSZSd_jjTVg/mqdefault.jpg",
          "width": 320,
          "height": 180
        },
        "high": {
          "url": "https://i.ytimg.com/vi/KSZSd_jjTVg/hqdefault.jpg",
          "width": 480,
          "height": 360
        }
      },
      "channelTitle": "iO - Technology",
      "liveBroadcastContent": "none",
      "publishTime": "2021-11-18T07:33:29Z",
      "id": "KSZSd_jjTVg"
    },
    {
      "publishedAt": "2021-11-12T07:52:02Z",
      "channelId": "UCNhy3hGzwMfbtX3Ei8Htcpg",
      "title": "Front-end meetup - Campus Eindhoven - 11/11/2021",
      "description": "15:40 – Dave Bitter (iO) – Dynamically generate Open Graph images using Next.js Serverless 1:14:46 - Maarten van Hoof ...",
      "thumbnails": {
        "default": {
          "url": "https://i.ytimg.com/vi/UuozuZm7xKU/default.jpg",
          "width": 120,
          "height": 90
        },
        "medium": {
          "url": "https://i.ytimg.com/vi/UuozuZm7xKU/mqdefault.jpg",
          "width": 320,
          "height": 180
        },
        "high": {
          "url": "https://i.ytimg.com/vi/UuozuZm7xKU/hqdefault.jpg",
          "width": 480,
          "height": 360
        }
      },
      "channelTitle": "iO - Technology",
      "liveBroadcastContent": "none",
      "publishTime": "2021-11-12T07:52:02Z",
      "id": "UuozuZm7xKU"
    },
    {
      "publishedAt": "2021-10-05T06:42:49Z",
      "channelId": "UCNhy3hGzwMfbtX3Ei8Htcpg",
      "title": "Dynamically generate Open Graph images using Next.js Serverless - Dave Bitter | GURU TALKS",
      "description": "We all know how you can add an OG image to your website. But did you know it's quite easy to generate custom, freshly designed ...",
      "thumbnails": {
        "default": {
          "url": "https://i.ytimg.com/vi/mTksuRErwG8/default.jpg",
          "width": 120,
          "height": 90
        },
        "medium": {
          "url": "https://i.ytimg.com/vi/mTksuRErwG8/mqdefault.jpg",
          "width": 320,
          "height": 180
        },
        "high": {
          "url": "https://i.ytimg.com/vi/mTksuRErwG8/hqdefault.jpg",
          "width": 480,
          "height": 360
        }
      },
      "channelTitle": "iO - Technology",
      "liveBroadcastContent": "none",
      "publishTime": "2021-10-05T06:42:49Z",
      "id": "mTksuRErwG8"
    },
    {
      "publishedAt": "2021-10-01T08:34:44Z",
      "channelId": "UCNhy3hGzwMfbtX3Ei8Htcpg",
      "title": "How Your Architecture &amp; Infra Can Make Your Team&#39;s Productivity - Jason Lengstorf | GURU TALKS",
      "description": "Healthy teams are high performers. Organizations that focus on team health gain a significant advantage in the market. But did ...",
      "thumbnails": {
        "default": {
          "url": "https://i.ytimg.com/vi/B2Tf6gyiKRY/default.jpg",
          "width": 120,
          "height": 90
        },
        "medium": {
          "url": "https://i.ytimg.com/vi/B2Tf6gyiKRY/mqdefault.jpg",
          "width": 320,
          "height": 180
        },
        "high": {
          "url": "https://i.ytimg.com/vi/B2Tf6gyiKRY/hqdefault.jpg",
          "width": 480,
          "height": 360
        }
      },
      "channelTitle": "iO - Technology",
      "liveBroadcastContent": "none",
      "publishTime": "2021-10-01T08:34:44Z",
      "id": "B2Tf6gyiKRY"
    },
    {
      "publishedAt": "2021-09-03T10:00:26Z",
      "channelId": "UCNhy3hGzwMfbtX3Ei8Htcpg",
      "title": "Creating multiscreen apps with the Presentation API | Friday Tips #12",
      "description": "In this thirteenth episode of Friday Tips: Dave Bitter, front-end developer at Frontmen (becoming iO), shows you how to create ...",
      "thumbnails": {
        "default": {
          "url": "https://i.ytimg.com/vi/qhq0PkxkplE/default.jpg",
          "width": 120,
          "height": 90
        },
        "medium": {
          "url": "https://i.ytimg.com/vi/qhq0PkxkplE/mqdefault.jpg",
          "width": 320,
          "height": 180
        },
        "high": {
          "url": "https://i.ytimg.com/vi/qhq0PkxkplE/hqdefault.jpg",
          "width": 480,
          "height": 360
        }
      },
      "channelTitle": "iO - Technology",
      "liveBroadcastContent": "none",
      "publishTime": "2021-09-03T10:00:26Z",
      "id": "qhq0PkxkplE"
    },
    {
      "publishedAt": "2021-08-27T10:00:30Z",
      "channelId": "UCNhy3hGzwMfbtX3Ei8Htcpg",
      "title": "A first look at the Shape Detection API | Friday Tips #11",
      "description": "In this twelfth episode of Friday Tips: Dave Bitter, front-end developer at Frontmen (becoming iO), shows you how to use the ...",
      "thumbnails": {
        "default": {
          "url": "https://i.ytimg.com/vi/ZnSTi3Wbs7g/default.jpg",
          "width": 120,
          "height": 90
        },
        "medium": {
          "url": "https://i.ytimg.com/vi/ZnSTi3Wbs7g/mqdefault.jpg",
          "width": 320,
          "height": 180
        },
        "high": {
          "url": "https://i.ytimg.com/vi/ZnSTi3Wbs7g/hqdefault.jpg",
          "width": 480,
          "height": 360
        }
      },
      "channelTitle": "iO - Technology",
      "liveBroadcastContent": "none",
      "publishTime": "2021-08-27T10:00:30Z",
      "id": "ZnSTi3Wbs7g"
    },
    {
      "publishedAt": "2021-08-27T06:23:45Z",
      "channelId": "UCNhy3hGzwMfbtX3Ei8Htcpg",
      "title": "Building Full Stack Apps on Ethereum with Next.js and Solidity - Nader Dabit | GURU TALKS",
      "description": "Decentralized apps (dApps) are continuing to gain momentum in the industry. These developers are also now some of the highest ...",
      "thumbnails": {
        "default": {
          "url": "https://i.ytimg.com/vi/1r_OlVbHd2s/default.jpg",
          "width": 120,
          "height": 90
        },
        "medium": {
          "url": "https://i.ytimg.com/vi/1r_OlVbHd2s/mqdefault.jpg",
          "width": 320,
          "height": 180
        },
        "high": {
          "url": "https://i.ytimg.com/vi/1r_OlVbHd2s/hqdefault.jpg",
          "width": 480,
          "height": 360
        }
      },
      "channelTitle": "iO - Technology",
      "liveBroadcastContent": "none",
      "publishTime": "2021-08-27T06:23:45Z",
      "id": "1r_OlVbHd2s"
    },
    {
      "publishedAt": "2021-08-20T10:00:14Z",
      "channelId": "UCNhy3hGzwMfbtX3Ei8Htcpg",
      "title": "Automate common code review chores with DangerJS | Friday Tips #10",
      "description": "In this eleventh episode of Friday Tips: Dave Bitter, front-end developer at Frontmen (becoming iO), shows you how to use ...",
      "thumbnails": {
        "default": {
          "url": "https://i.ytimg.com/vi/J2ITov8r0Rs/default.jpg",
          "width": 120,
          "height": 90
        },
        "medium": {
          "url": "https://i.ytimg.com/vi/J2ITov8r0Rs/mqdefault.jpg",
          "width": 320,
          "height": 180
        },
        "high": {
          "url": "https://i.ytimg.com/vi/J2ITov8r0Rs/hqdefault.jpg",
          "width": 480,
          "height": 360
        }
      },
      "channelTitle": "iO - Technology",
      "liveBroadcastContent": "none",
      "publishTime": "2021-08-20T10:00:14Z",
      "id": "J2ITov8r0Rs"
    },
    {
      "publishedAt": "2021-08-13T10:00:05Z",
      "channelId": "UCNhy3hGzwMfbtX3Ei8Htcpg",
      "title": "Visual regression testing with Chromatic for Storybook | Friday Tips #9",
      "description": "In this tenth episode of Friday Tips: Dave Bitter, front-end developer at Frontmen (becoming iO), shows you how to use Chromatic ...",
      "thumbnails": {
        "default": {
          "url": "https://i.ytimg.com/vi/AGyUh_ta3TU/default.jpg",
          "width": 120,
          "height": 90
        },
        "medium": {
          "url": "https://i.ytimg.com/vi/AGyUh_ta3TU/mqdefault.jpg",
          "width": 320,
          "height": 180
        },
        "high": {
          "url": "https://i.ytimg.com/vi/AGyUh_ta3TU/hqdefault.jpg",
          "width": 480,
          "height": 360
        }
      },
      "channelTitle": "iO - Technology",
      "liveBroadcastContent": "none",
      "publishTime": "2021-08-13T10:00:05Z",
      "id": "AGyUh_ta3TU"
    },
    {
      "publishedAt": "2021-08-06T10:00:14Z",
      "channelId": "UCNhy3hGzwMfbtX3Ei8Htcpg",
      "title": "CodeTour Visual Studio Code extension | Friday Tips #8",
      "description": "In this ninth episode of Friday Tips: Dave Bitter, front-end developer at Frontmen (becoming iO), shows you how to use the Visual ...",
      "thumbnails": {
        "default": {
          "url": "https://i.ytimg.com/vi/c2J_o7ZkBbM/default.jpg",
          "width": 120,
          "height": 90
        },
        "medium": {
          "url": "https://i.ytimg.com/vi/c2J_o7ZkBbM/mqdefault.jpg",
          "width": 320,
          "height": 180
        },
        "high": {
          "url": "https://i.ytimg.com/vi/c2J_o7ZkBbM/hqdefault.jpg",
          "width": 480,
          "height": 360
        }
      },
      "channelTitle": "iO - Technology",
      "liveBroadcastContent": "none",
      "publishTime": "2021-08-06T10:00:14Z",
      "id": "c2J_o7ZkBbM"
    },
    {
      "publishedAt": "2021-07-30T10:00:08Z",
      "channelId": "UCNhy3hGzwMfbtX3Ei8Htcpg",
      "title": "Just use the native Intl API for formatting dates, number and currencies  | Friday Tips #7",
      "description": "In this eighth episode of Friday Tips: Dave Bitter, front-end developer at Frontmen (becoming iO), shows you how to use the native ...",
      "thumbnails": {
        "default": {
          "url": "https://i.ytimg.com/vi/M-y4aU02cjI/default.jpg",
          "width": 120,
          "height": 90
        },
        "medium": {
          "url": "https://i.ytimg.com/vi/M-y4aU02cjI/mqdefault.jpg",
          "width": 320,
          "height": 180
        },
        "high": {
          "url": "https://i.ytimg.com/vi/M-y4aU02cjI/hqdefault.jpg",
          "width": 480,
          "height": 360
        }
      },
      "channelTitle": "iO - Technology",
      "liveBroadcastContent": "none",
      "publishTime": "2021-07-30T10:00:08Z",
      "id": "M-y4aU02cjI"
    },
    {
      "publishedAt": "2021-07-23T10:00:01Z",
      "channelId": "UCNhy3hGzwMfbtX3Ei8Htcpg",
      "title": "Scaffolding with PlopJS | Friday Tips #6",
      "description": "In this seventh episode of Friday Tips: Dave Bitter, front-end developer at Frontmen (becoming iO), shows you how to automate ...",
      "thumbnails": {
        "default": {
          "url": "https://i.ytimg.com/vi/4cYwYKAT2X4/default.jpg",
          "width": 120,
          "height": 90
        },
        "medium": {
          "url": "https://i.ytimg.com/vi/4cYwYKAT2X4/mqdefault.jpg",
          "width": 320,
          "height": 180
        },
        "high": {
          "url": "https://i.ytimg.com/vi/4cYwYKAT2X4/hqdefault.jpg",
          "width": 480,
          "height": 360
        }
      },
      "channelTitle": "iO - Technology",
      "liveBroadcastContent": "none",
      "publishTime": "2021-07-23T10:00:01Z",
      "id": "4cYwYKAT2X4"
    },
    {
      "publishedAt": "2021-07-16T09:00:22Z",
      "channelId": "UCNhy3hGzwMfbtX3Ei8Htcpg",
      "title": "Update your GitHub README with GitHub actions | Friday Tips #5",
      "description": "In this sixth episode of Friday Tips: Dave Bitter, front-end developer at Frontmen (becoming iO), shows you how you can use ...",
      "thumbnails": {
        "default": {
          "url": "https://i.ytimg.com/vi/jVg-qkQ01lI/default.jpg",
          "width": 120,
          "height": 90
        },
        "medium": {
          "url": "https://i.ytimg.com/vi/jVg-qkQ01lI/mqdefault.jpg",
          "width": 320,
          "height": 180
        },
        "high": {
          "url": "https://i.ytimg.com/vi/jVg-qkQ01lI/hqdefault.jpg",
          "width": 480,
          "height": 360
        }
      },
      "channelTitle": "iO - Technology",
      "liveBroadcastContent": "none",
      "publishTime": "2021-07-16T09:00:22Z",
      "id": "jVg-qkQ01lI"
    },
    {
      "publishedAt": "2021-07-15T18:13:52Z",
      "channelId": "UCNhy3hGzwMfbtX3Ei8Htcpg",
      "title": "End-to-End Testing for a Real-time Chat Web Application - Gleb Bahmutov | GURU TALKS",
      "description": "Using Cypress to test a real-time chat web application implemented using WebSockets. We will see how the test runner can act as ...",
      "thumbnails": {
        "default": {
          "url": "https://i.ytimg.com/vi/fA-JN6GFO9A/default.jpg",
          "width": 120,
          "height": 90
        },
        "medium": {
          "url": "https://i.ytimg.com/vi/fA-JN6GFO9A/mqdefault.jpg",
          "width": 320,
          "height": 180
        },
        "high": {
          "url": "https://i.ytimg.com/vi/fA-JN6GFO9A/hqdefault.jpg",
          "width": 480,
          "height": 360
        }
      },
      "channelTitle": "iO - Technology",
      "liveBroadcastContent": "none",
      "publishTime": "2021-07-15T18:13:52Z",
      "id": "fA-JN6GFO9A"
    },
    {
      "publishedAt": "2021-07-15T18:14:03Z",
      "channelId": "UCNhy3hGzwMfbtX3Ei8Htcpg",
      "title": "Authentication for JS developers - Niek Heezemans | GURU TALKS",
      "description": "Oauth 2.0, Social Login with OpenID Connect or Passwordless? Niek will go over the different ways/protocols of authentication ...",
      "thumbnails": {
        "default": {
          "url": "https://i.ytimg.com/vi/0QS9XOraCMc/default.jpg",
          "width": 120,
          "height": 90
        },
        "medium": {
          "url": "https://i.ytimg.com/vi/0QS9XOraCMc/mqdefault.jpg",
          "width": 320,
          "height": 180
        },
        "high": {
          "url": "https://i.ytimg.com/vi/0QS9XOraCMc/hqdefault.jpg",
          "width": 480,
          "height": 360
        }
      },
      "channelTitle": "iO - Technology",
      "liveBroadcastContent": "none",
      "publishTime": "2021-07-15T18:14:03Z",
      "id": "0QS9XOraCMc"
    },
    {
      "publishedAt": "2021-07-09T09:00:26Z",
      "channelId": "UCNhy3hGzwMfbtX3Ei8Htcpg",
      "title": "Short introduction to React Query | Friday Tips #4",
      "description": "In this fifth episode of Friday Tips: Dave Bitter, front-end developer at Frontmen (becoming iO), shows you how you can use React ...",
      "thumbnails": {
        "default": {
          "url": "https://i.ytimg.com/vi/Rttu1fVRyvw/default.jpg",
          "width": 120,
          "height": 90
        },
        "medium": {
          "url": "https://i.ytimg.com/vi/Rttu1fVRyvw/mqdefault.jpg",
          "width": 320,
          "height": 180
        },
        "high": {
          "url": "https://i.ytimg.com/vi/Rttu1fVRyvw/hqdefault.jpg",
          "width": 480,
          "height": 360
        }
      },
      "channelTitle": "iO - Technology",
      "liveBroadcastContent": "none",
      "publishTime": "2021-07-09T09:00:26Z",
      "id": "Rttu1fVRyvw"
    },
    {
      "publishedAt": "2021-07-08T11:53:29Z",
      "channelId": "UCNhy3hGzwMfbtX3Ei8Htcpg",
      "title": "Deno Q&amp;A - Luca Casonato | GURU TALKS",
      "description": "Luca Casonato, from the Deno Core team, did a Q&A with us. Questions were send in and this way you get a good overview of the ...",
      "thumbnails": {
        "default": {
          "url": "https://i.ytimg.com/vi/iYKt0Qd5ucM/default.jpg",
          "width": 120,
          "height": 90
        },
        "medium": {
          "url": "https://i.ytimg.com/vi/iYKt0Qd5ucM/mqdefault.jpg",
          "width": 320,
          "height": 180
        },
        "high": {
          "url": "https://i.ytimg.com/vi/iYKt0Qd5ucM/hqdefault.jpg",
          "width": 480,
          "height": 360
        }
      },
      "channelTitle": "iO - Technology",
      "liveBroadcastContent": "none",
      "publishTime": "2021-07-08T11:53:29Z",
      "id": "iYKt0Qd5ucM"
    },
    {
      "publishedAt": "2021-07-02T09:00:25Z",
      "channelId": "UCNhy3hGzwMfbtX3Ei8Htcpg",
      "title": "Quickly start new projects with GitHub template repositories | Friday Tips #3",
      "description": "In this fourth episode of Friday Tips: Dave Bitter, front-end developer at Frontmen (becoming iO), shows you how you can use ...",
      "thumbnails": {
        "default": {
          "url": "https://i.ytimg.com/vi/zCKwIApdNXw/default.jpg",
          "width": 120,
          "height": 90
        },
        "medium": {
          "url": "https://i.ytimg.com/vi/zCKwIApdNXw/mqdefault.jpg",
          "width": 320,
          "height": 180
        },
        "high": {
          "url": "https://i.ytimg.com/vi/zCKwIApdNXw/hqdefault.jpg",
          "width": 480,
          "height": 360
        }
      },
      "channelTitle": "iO - Technology",
      "liveBroadcastContent": "none",
      "publishTime": "2021-07-02T09:00:25Z",
      "id": "zCKwIApdNXw"
    },
    {
      "publishedAt": "2021-06-25T09:00:01Z",
      "channelId": "UCNhy3hGzwMfbtX3Ei8Htcpg",
      "title": "Retrieve billing info with the Payment Request API | Friday Tips #2",
      "description": "In this third episode of Friday Tips: Dave Bitter, front-end developer at Frontmen (becoming iO), shows you how you can retrieve ...",
      "thumbnails": {
        "default": {
          "url": "https://i.ytimg.com/vi/-yB0KrCuu7o/default.jpg",
          "width": 120,
          "height": 90
        },
        "medium": {
          "url": "https://i.ytimg.com/vi/-yB0KrCuu7o/mqdefault.jpg",
          "width": 320,
          "height": 180
        },
        "high": {
          "url": "https://i.ytimg.com/vi/-yB0KrCuu7o/hqdefault.jpg",
          "width": 480,
          "height": 360
        }
      },
      "channelTitle": "iO - Technology",
      "liveBroadcastContent": "none",
      "publishTime": "2021-06-25T09:00:01Z",
      "id": "-yB0KrCuu7o"
    },
    {
      "publishedAt": "2021-06-18T09:00:25Z",
      "channelId": "UCNhy3hGzwMfbtX3Ei8Htcpg",
      "title": "Quokka.js Visual Studio Code extension | Friday Tips #1",
      "description": "In this second episode of Friday Tips: Dave Bitter, front-end developer at Frontmen (becoming iO), shows you how to you can use ...",
      "thumbnails": {
        "default": {
          "url": "https://i.ytimg.com/vi/bN695JOSyw4/default.jpg",
          "width": 120,
          "height": 90
        },
        "medium": {
          "url": "https://i.ytimg.com/vi/bN695JOSyw4/mqdefault.jpg",
          "width": 320,
          "height": 180
        },
        "high": {
          "url": "https://i.ytimg.com/vi/bN695JOSyw4/hqdefault.jpg",
          "width": 480,
          "height": 360
        }
      },
      "channelTitle": "iO - Technology",
      "liveBroadcastContent": "none",
      "publishTime": "2021-06-18T09:00:25Z",
      "id": "bN695JOSyw4"
    },
    {
      "publishedAt": "2021-06-11T10:00:31Z",
      "channelId": "UCNhy3hGzwMfbtX3Ei8Htcpg",
      "title": "How to create a GitHub profile README | Friday Tips #0",
      "description": "In this first episode of Friday Tips: Dave Bitter, front-end developer at Frontmen (becoming iO), shows you how to create a GitHub ...",
      "thumbnails": {
        "default": {
          "url": "https://i.ytimg.com/vi/ewtT4NJX6NA/default.jpg",
          "width": 120,
          "height": 90
        },
        "medium": {
          "url": "https://i.ytimg.com/vi/ewtT4NJX6NA/mqdefault.jpg",
          "width": 320,
          "height": 180
        },
        "high": {
          "url": "https://i.ytimg.com/vi/ewtT4NJX6NA/hqdefault.jpg",
          "width": 480,
          "height": 360
        }
      },
      "channelTitle": "iO - Technology",
      "liveBroadcastContent": "none",
      "publishTime": "2021-06-11T10:00:31Z",
      "id": "ewtT4NJX6NA"
    },
    {
      "publishedAt": "2021-06-04T11:01:31Z",
      "channelId": "UCNhy3hGzwMfbtX3Ei8Htcpg",
      "title": "Third Age of Javascript - Shawn Wang | GURU TALKS",
      "description": "Shawn, better known as swyx, has some really interesting thoughts about what the future of the web will look like. He talked about ...",
      "thumbnails": {
        "default": {
          "url": "https://i.ytimg.com/vi/3IOb6bzeBy0/default.jpg",
          "width": 120,
          "height": 90
        },
        "medium": {
          "url": "https://i.ytimg.com/vi/3IOb6bzeBy0/mqdefault.jpg",
          "width": 320,
          "height": 180
        },
        "high": {
          "url": "https://i.ytimg.com/vi/3IOb6bzeBy0/hqdefault.jpg",
          "width": 480,
          "height": 360
        }
      },
      "channelTitle": "iO - Technology",
      "liveBroadcastContent": "none",
      "publishTime": "2021-06-04T11:01:31Z",
      "id": "3IOb6bzeBy0"
    },
    {
      "publishedAt": "2021-04-30T10:30:30Z",
      "channelId": "UCNhy3hGzwMfbtX3Ei8Htcpg",
      "title": "Coming Soon to CSS - Rachel Andrew | GURU TALKS",
      "description": "Rachel Andrew, who doesn't know her? We had the pleasure to get inspired by some awesome new features available or coming ...",
      "thumbnails": {
        "default": {
          "url": "https://i.ytimg.com/vi/DjCaG6z_n-Q/default.jpg",
          "width": 120,
          "height": 90
        },
        "medium": {
          "url": "https://i.ytimg.com/vi/DjCaG6z_n-Q/mqdefault.jpg",
          "width": 320,
          "height": 180
        },
        "high": {
          "url": "https://i.ytimg.com/vi/DjCaG6z_n-Q/hqdefault.jpg",
          "width": 480,
          "height": 360
        }
      },
      "channelTitle": "iO - Technology",
      "liveBroadcastContent": "none",
      "publishTime": "2021-04-30T10:30:30Z",
      "id": "DjCaG6z_n-Q"
    },
    {
      "publishedAt": "2021-04-05T06:00:03Z",
      "channelId": "UCNhy3hGzwMfbtX3Ei8Htcpg",
      "title": "State of Vue.JS 2021 - Ben Hong | GURU TALKS",
      "description": "Ben Hong, Netlify developer and Vue Core Team member, gave an introduction into VueJS including the Composition API.",
      "thumbnails": {
        "default": {
          "url": "https://i.ytimg.com/vi/MIyQlSCcuS0/default.jpg",
          "width": 120,
          "height": 90
        },
        "medium": {
          "url": "https://i.ytimg.com/vi/MIyQlSCcuS0/mqdefault.jpg",
          "width": 320,
          "height": 180
        },
        "high": {
          "url": "https://i.ytimg.com/vi/MIyQlSCcuS0/hqdefault.jpg",
          "width": 480,
          "height": 360
        }
      },
      "channelTitle": "iO - Technology",
      "liveBroadcastContent": "none",
      "publishTime": "2021-04-05T06:00:03Z",
      "id": "MIyQlSCcuS0"
    },
    {
      "publishedAt": "2021-04-01T06:00:01Z",
      "channelId": "UCNhy3hGzwMfbtX3Ei8Htcpg",
      "title": "Accessibility 101 - Nicolas Steenhout | GURU TALKS",
      "description": "Nicolas Steenhout, a guru about a11y, explains why a11y is so important and shares insights in how to make your apps better.",
      "thumbnails": {
        "default": {
          "url": "https://i.ytimg.com/vi/a3JneJFea1Q/default.jpg",
          "width": 120,
          "height": 90
        },
        "medium": {
          "url": "https://i.ytimg.com/vi/a3JneJFea1Q/mqdefault.jpg",
          "width": 320,
          "height": 180
        },
        "high": {
          "url": "https://i.ytimg.com/vi/a3JneJFea1Q/hqdefault.jpg",
          "width": 480,
          "height": 360
        }
      },
      "channelTitle": "iO - Technology",
      "liveBroadcastContent": "none",
      "publishTime": "2021-04-01T06:00:01Z",
      "id": "a3JneJFea1Q"
    },
    {
      "publishedAt": "2021-03-29T06:00:06Z",
      "channelId": "UCNhy3hGzwMfbtX3Ei8Htcpg",
      "title": "Mock to start - Murat Çorlu | GURU TALKS",
      "description": "Murat Çorlu (Frontmen developer) created his own mocking library with some interesting features. In this talk he gives an ...",
      "thumbnails": {
        "default": {
          "url": "https://i.ytimg.com/vi/yn8aOMM3asw/default.jpg",
          "width": 120,
          "height": 90
        },
        "medium": {
          "url": "https://i.ytimg.com/vi/yn8aOMM3asw/mqdefault.jpg",
          "width": 320,
          "height": 180
        },
        "high": {
          "url": "https://i.ytimg.com/vi/yn8aOMM3asw/hqdefault.jpg",
          "width": 480,
          "height": 360
        }
      },
      "channelTitle": "iO - Technology",
      "liveBroadcastContent": "none",
      "publishTime": "2021-03-29T06:00:06Z",
      "id": "yn8aOMM3asw"
    },
    {
      "publishedAt": "2021-03-25T07:00:03Z",
      "channelId": "UCNhy3hGzwMfbtX3Ei8Htcpg",
      "title": "Blitz, the Fullstack React framework - Brandon Bayer | GURU TALKS",
      "description": "Brandon Bayer (creator of Blitz) gave an awesome overview of all the great features of Blitz. Just 2 weeks before the beta release ...",
      "thumbnails": {
        "default": {
          "url": "https://i.ytimg.com/vi/Jc0byVRqa70/default.jpg",
          "width": 120,
          "height": 90
        },
        "medium": {
          "url": "https://i.ytimg.com/vi/Jc0byVRqa70/mqdefault.jpg",
          "width": 320,
          "height": 180
        },
        "high": {
          "url": "https://i.ytimg.com/vi/Jc0byVRqa70/hqdefault.jpg",
          "width": 480,
          "height": 360
        }
      },
      "channelTitle": "iO - Technology",
      "liveBroadcastContent": "none",
      "publishTime": "2021-03-25T07:00:03Z",
      "id": "Jc0byVRqa70"
    },
    {
      "publishedAt": "2021-03-22T07:00:35Z",
      "channelId": "UCNhy3hGzwMfbtX3Ei8Htcpg",
      "title": "Pipe it, curry it, tacit - Abbe Keultjes | GURU TALKS",
      "description": "Abbe Keultjes (Frontmen developer) is a big fan of functional programming. In this video he explains step by step how to refactor ...",
      "thumbnails": {
        "default": {
          "url": "https://i.ytimg.com/vi/vgXcjzdZvYo/default.jpg",
          "width": 120,
          "height": 90
        },
        "medium": {
          "url": "https://i.ytimg.com/vi/vgXcjzdZvYo/mqdefault.jpg",
          "width": 320,
          "height": 180
        },
        "high": {
          "url": "https://i.ytimg.com/vi/vgXcjzdZvYo/hqdefault.jpg",
          "width": 480,
          "height": 360
        }
      },
      "channelTitle": "iO - Technology",
      "liveBroadcastContent": "none",
      "publishTime": "2021-03-22T07:00:35Z",
      "id": "vgXcjzdZvYo"
    },
    {
      "publishedAt": "2021-03-18T07:00:07Z",
      "channelId": "UCNhy3hGzwMfbtX3Ei8Htcpg",
      "title": "NearleyJS Parser - Jurgen Beliën | GURU TALKS",
      "description": "Jurgen Beliën (Frontmen developer) previously used NearlyJS to write an interface for a quantum computer. In this talk he ...",
      "thumbnails": {
        "default": {
          "url": "https://i.ytimg.com/vi/jZXPkWkluLE/default.jpg",
          "width": 120,
          "height": 90
        },
        "medium": {
          "url": "https://i.ytimg.com/vi/jZXPkWkluLE/mqdefault.jpg",
          "width": 320,
          "height": 180
        },
        "high": {
          "url": "https://i.ytimg.com/vi/jZXPkWkluLE/hqdefault.jpg",
          "width": 480,
          "height": 360
        }
      },
      "channelTitle": "iO - Technology",
      "liveBroadcastContent": "none",
      "publishTime": "2021-03-18T07:00:07Z",
      "id": "jZXPkWkluLE"
    },
    {
      "publishedAt": "2021-03-15T07:00:09Z",
      "channelId": "UCNhy3hGzwMfbtX3Ei8Htcpg",
      "title": "NextJS in Production - Scott Moss | GURU TALKS",
      "description": "In this talk, Scott Moss (Netflix developer) shows some of the awesome features of NextJS and things he ran into while developing ...",
      "thumbnails": {
        "default": {
          "url": "https://i.ytimg.com/vi/nPooaqHb7aM/default.jpg",
          "width": 120,
          "height": 90
        },
        "medium": {
          "url": "https://i.ytimg.com/vi/nPooaqHb7aM/mqdefault.jpg",
          "width": 320,
          "height": 180
        },
        "high": {
          "url": "https://i.ytimg.com/vi/nPooaqHb7aM/hqdefault.jpg",
          "width": 480,
          "height": 360
        }
      },
      "channelTitle": "iO - Technology",
      "liveBroadcastContent": "none",
      "publishTime": "2021-03-15T07:00:09Z",
      "id": "nPooaqHb7aM"
    },
    {
      "publishedAt": "2021-03-06T23:00:02Z",
      "channelId": "UCNhy3hGzwMfbtX3Ei8Htcpg",
      "title": "Dark mode on the web - Tom Herni | GURU TALKS",
      "description": "In this talk, Tom Herni (Frontmen developer) explains why you should support Dark Mode and how to implement it in your web ...",
      "thumbnails": {
        "default": {
          "url": "https://i.ytimg.com/vi/94l_lENf9fI/default.jpg",
          "width": 120,
          "height": 90
        },
        "medium": {
          "url": "https://i.ytimg.com/vi/94l_lENf9fI/mqdefault.jpg",
          "width": 320,
          "height": 180
        },
        "high": {
          "url": "https://i.ytimg.com/vi/94l_lENf9fI/hqdefault.jpg",
          "width": 480,
          "height": 360
        }
      },
      "channelTitle": "iO - Technology",
      "liveBroadcastContent": "none",
      "publishTime": "2021-03-06T23:00:02Z",
      "id": "94l_lENf9fI"
    },
    {
      "publishedAt": "2021-03-05T11:39:17Z",
      "channelId": "UCNhy3hGzwMfbtX3Ei8Htcpg",
      "title": "Smooth design hand off with Storybook - Yann Braga | GURU TALKS",
      "description": "In this talk Yann Braga (Frontmen developer and Storybook contributor) shows some of the great ways to use Storybook and ...",
      "thumbnails": {
        "default": {
          "url": "https://i.ytimg.com/vi/2LBBrIulDe0/default.jpg",
          "width": 120,
          "height": 90
        },
        "medium": {
          "url": "https://i.ytimg.com/vi/2LBBrIulDe0/mqdefault.jpg",
          "width": 320,
          "height": 180
        },
        "high": {
          "url": "https://i.ytimg.com/vi/2LBBrIulDe0/hqdefault.jpg",
          "width": 480,
          "height": 360
        }
      },
      "channelTitle": "iO - Technology",
      "liveBroadcastContent": "none",
      "publishTime": "2021-03-05T11:39:17Z",
      "id": "2LBBrIulDe0"
    }
  ]
}
